AUTHORS
LICENSE
README.md
setup.py
krules_flask_env/__init__.py
krules_flask_env/app.py
krules_flask_env.egg-info/PKG-INFO
krules_flask_env.egg-info/SOURCES.txt
krules_flask_env.egg-info/dependency_links.txt
krules_flask_env.egg-info/requires.txt
krules_flask_env.egg-info/top_level.txt