Metadata-Version: 2.1
Name: krules-flask-env
Version: 0.11
Summary: KRules environment base package
Home-page: https://github.com/airspot-dev/krules-flask-env
Author: Alberto Degli Esposti
Author-email: alberto@arispot.tech
License: Apache Licence 2.0
Keywords: krules rules engine flask
Platform: UNKNOWN
Classifier: Development Status :: 3 - Alpha
Classifier: License :: OSI Approved :: Apache Software License
License-File: LICENSE
License-File: AUTHORS
